pansql/__init__.py
pansql/sqldf.py
pansql/data/births.csv
pansql/data/births_by_month.csv
pansql/data/meat.csv
pansql/tests/__init__.py
pansql/tests/test_pandasql.py
pansql/tests/test_utils.py
pansql-0.0.1.dist-info/AUTHORS.md
pansql-0.0.1.dist-info/LICENSE.txt
pansql-0.0.1.dist-info/METADATA
pansql-0.0.1.dist-info/WHEEL
pansql-0.0.1.dist-info/top_level.txt
pansql-0.0.1.dist-info/RECORD
