Metadata-Version: 2.1
Name: pansql
Version: 0.0.1
Summary: sqldf for pandas
Home-page: https://github.com/hrshdhgd/pansql/
Author: Harshad Hegde
Author-email: hhegde@lbl.gov
License: MIT
Classifier: License :: OSI Approved :: MIT License
License-File: LICENSE.txt
License-File: AUTHORS.md
Requires-Dist: numpy
Requires-Dist: pandas
Requires-Dist: sqlalchemy
